{
  "meta": {
    "language": "lv",
    "title": "Aleksejs Babenko | Portfolio"
  },
  "nav": {
    "home": "Sākums",
    "about": "Par mani",
    "portfolio": "Portfolio",
    "contact": "Kontakti"
  },
  "home": {
    "name": "Aleksejs Babenko",
    "title": "Portfolio"
  },
  "about": {
    "title": "Par mani",
    "work": {
      "title": "Darbs"
    },
    "education": {
      "title": "Izglītība",
      "items": [
        {
          "degree": "Sociālo zinātņu maģistra grāds vadībzinātnē",
          "institution": "Transporta un sakaru institūts",
          "period": "2003 – 2009",
          "additionalInfo": [
            "Absolvēju ar izcilību.",
            "Saņēmu 2 grantus:",
            "par augstām sekmēm un zinātnisko darbību (Parex Banka fonds)",
            "par izciliem sasniegumiem matemātikas priekšmetos (Haima Kordonska fonds, ASV)",
            "Piedalījos 4 zinātniskās konferencēs un publicēju 3 zinātniskos rakstus."
          ]
        },
        {
          "degree": "Radioelektronikas inženieris",
          "institution": "Rīgas Tehniskā koledža",
          "period": "1991 – 1996",
          "additionalInfo": [
            "5 gadu pilna inženiera programma",
            "Konkurss iestājējos: 4,5 cilvēki uz vietu"
          ]
        }
      ]
    },
    "languages": {
      "title": "Valodu prasmes",
      "items": [
        {
          "name": "Latviešu valoda",
          "level": "C1",
          "percentage": 85
        },
        {
          "name": "Angļu valoda",
          "level": "B2",
          "percentage": 70
        },
        {
          "name": "Krievu valoda",
          "level": "Dzimtā",
          "percentage": 100
        }
      ]
    },
    "skills": {
      "title": "Citas prasmes",
      "categories": [
        {
          "name": "Vadības un komunikācijas prasmes",
          "items": [
            "Laika plānošana un uzdevumu prioritizēšana (kurss «Time-Management un operatīva plānošana», Amadeus Group)",
            "Darbs ar klientiem un piegādātājiem",
            "Atskaišu un dokumentācijas sagatavošana",
            "Finanšu atskaišu analīze un investīciju izvērtēšana",
            "Kvalitātes un termiņu kontrole",
            "Preču un pakalpojumu prezentāciju vadīšana",
            "Uzņēmuma izveide un vadība"
          ]
        },
        {
          "name": "Datorprasmes",
          "items": [
            "Datoru sistēmu montāža un konfigurēšana",
            "Operētājsistēmu (Windows, MacOS, Linux) ekspluatācija un apkalpošana",
            "MS Excel padziļinātas zināšanas",
            "Rūteru iestatīšana (t.sk. Mikrotik) un tīkla aprīkojums",
            "TV, video un audio iekārtu konfigurēšana"
          ]
        },
        {
          "name": "Tehniskās prasmes",
          "items": [
            "Tīkla projektēšana un realizācija",
            "Elektronisko un drošības iekārtu montāža un uzstādīšana (TV, kameras, seifi)",
            "Elektroiekārtu un vājstrāvas kabeļu uzstādīšana",
            "Biroja un ražošanas aprīkojuma tehniskā apkope un uzturēšana",
            "Darbs ar instrumentiem un tehnisko remontu veikšana"
          ]
        },
        {
          "name": "Poligrāfijas prasmes",
          "items": [
            "Darbs ar lielformāta un UV printeriem (Roland, Epson, Mimaki)",
            "CTP sistēmu ekspluatācija un apkalpošana",
            "Failu sagatavošana drukai un fleksogrāfijas dizainu izstrāde",
            "Pantone paraugu sagatavošana, krāsu dalīšana un korekcija",
            "Lappušu izkārtojuma sagatavošana drukai (Adobe Acrobat, QuarkXPress, Prinect Signa Station)"
          ]
        },
        {
          "name": "Datorgrafika un dizains",
          "items": [
            "Videoreklāmas izstrāde un apstrāde – Adobe After Effects",
            "Dizains drukas materiāliem (plakāti, vizītkartes, bukleti, uzlīmes) – CorelDRAW, Illustrator",
            "Baneru dizains internetam, tai skaitā animētie baneri",
            "Prezentāciju izstrāde – Microsoft PowerPoint",
            "Attēlu apstrāde un retušēšana – Adobe Photoshop"
          ]
        },
        {
          "name": "Papildu informācija",
          "items": [
            "B kategorijas autovadītāja apliecība"
          ]
        }
      ]
    },
    "interests": {
      "title": "Hobiji un interesi",
      "categories": [
        {
          "name": "Sports",
          "items": [
            {
              "name": "Skriešana",
              "icon": "fas fa-running"
            },
            {
              "name": "Trenažieri",
              "icon": "fas fa-dumbbell"
            },
            {
              "name": "Futbols",
              "icon": "fas fa-futbol"
            }
          ]
        }
      ],
      "singleItems": [
        {
          "name": "Laiks ar ģimeni",
          "icon": "fa-solid fa-people-roof"
        },
        {
          "name": "Valodu apgūšana",
          "icon": "fas fa-language"
        }
      ]
    },
    "experience": [
      {
        "period": "2024 – 2025",
        "position": "Iespiedējs",
        "company": "Pro-Baltic",
        "duration": "1 gads un 4 mēneši",
        "additionalInfo": [
          {
            "type": "text",
            "content": "Īsā laikā apguvu specializētās poligrāfijas iekārtas (Mimaki) darbību visos tehniskajos aspektos un niansēs."
          },
          {
            "type": "text",
            "content": "Ierobežotais uzdevumu klāsts kļuva par izaicinājumu meklēt optimizācijas iespējas. Ieviestie uzlabojumi ļāva:"
          },
          {
            "type": "list",
            "items": [
              "Paaugstināt darba procesu efektivitāti",
              "Samazināt pasūtījumu izpildes termiņus",
              "Uzlabot produkcijas kvalitāti un kontroles līmeni"
            ]
          }
        ]
      },
      {
        "period": "2012 – 2023",
        "position": "Tehniskais speciālists",
        "company": "Optibet",
        "duration": "11 gadi un 2 mēneši",
        "additionalInfo": [
          {
            "type": "text",
            "content": "Darbs starptautiskā kompānijā man sniedza daudzpusīgāko pieredzi. Veicu gan individuālus uzdevumus, gan komandu projektus."
          },
          {
            "type": "text",
            "content": "Galvenie pienākumi un sasniegumi:"
          },
          {
            "type": "list",
            "items": [
              "Jaunu filiāļu atvēršana: projektēšana, tehniskais aprīkojums, uzstādīšana un nodošana ekspluatācijā",
              "Sadarbība ar dažādām uzņēmuma nodaļām un ārējiem partneriem",
              "Iekšējo projektu izstrāde Windows, Linux un Android vidē",
              "Kases sistēmu uzstādīšana un konfigurēšana",
              "Videoreklāmu un mārketinga materiālu izstrāde",
              "Iekārtu stāvokļa monitorings un datu dublēšana",
              "Bāru preču apgādes organizēšana un uzskaite",
              "Konsultēšana, tehniskais atbalsts un personāla apmācība",
              "Regulāri darba komandējumi pa Latviju un Lietuvu"
            ]
          },
          {
            "type": "text",
            "content": "Ar saviem kolēģiem mēs bijām ne tikai kolektīvs, bet arī īsta komanda — saliedēta, draudzīga un profesionāla. Tieši to es uzskatu par savu lielāko ieguvumu."
          }
        ]
      },
      {
        "period": "2009 – 2022",
        "position": "Vadītājs",
        "company": "Bob.lv",
        "duration": "13 gadi un 3 mēneši",
        "additionalInfo": [
          {
            "type": "text",
            "content": "Pēc maģistra grāda iegūšanas nodibināju kompāniju Bob.lv, kas klientiem piedāvāja pilnu poligrāfijas pakalpojumu klāstu, strādājot bez savām iekārtām."
          },
          {
            "type": "text",
            "content": "Galvenie darbības aspekti:"
          },
          {
            "type": "list",
            "items": [
              "Visu procesu koordinēšana: no dizaina un komunikācijas ar klientiem līdz drukas kvalitātes kontrolei pie partneriem",
              "Finanšu pārvaldība: rēķinu un dokumentu aprites vadīšana, norēķini ar piegādātājiem un klientiem"
            ]
          },
          {
            "type": "text",
            "content": "Ieguvu vērtīgu pieredzi uzņēmējdarbībā un operatīvā vadībā, apvienojot to ar praktisko darbu dizaina jomā."
          }
        ]
      },
      {
        "period": "2008 – 2009",
        "position": "Pirmsdrukas meistars",
        "company": "Poligrāfijas grupa Fenster",
        "duration": "1 gads un 5 mēneši",
        "additionalInfo": [
          {
            "type": "text",
            "content": "Saņēmu piedāvājumu atgriezties savā bijušajā kolektīvā – pirmsdrukas sagatavošanas nodaļā. Izdevniecība uzsāka savas avīžu tipogrāfijas darbību, kurā tika ieviesta moderna Computer-to-Plate (CTP) tehnoloģija tiešai iespiedformu izgatavošanai."
          },
          {
            "type": "text",
            "content": "Jaunie virzieni:"
          },
          {
            "type": "list",
            "items": [
              "Lappušu montāža un formu drukāšana (Computer-to-Plate, CTP)",
              "CTP iekārtu kontrole un apkalpošana"
            ]
          },
          {
            "type": "text",
            "content": "Iepriekšējie uzdevumi:"
          },
          {
            "type": "list",
            "items": [
              "Lielformāta druka (plakāti, baneri, uzlīmes)",
              "Filmu drukāšana pasūtītājiem",
              "Darbs ar klientiem",
              "Iekārtu apkalpošana"
            ]
          }
        ]
      },
      {
        "period": "2006 – 2007",
        "position": "Vecākais fleksogrāfijas maketētājs",
        "company": "Impress",
        "duration": "1 gads un 2 mēneši",
        "additionalInfo": [
          {
            "type": "text",
            "content": "Pārgāju uz uzņēmumu pēc bijušā kolēģa uzaicinājuma, kas kļuva par manu profesionālo īpašību atzīšanu. Apguvu pilnīgi jaunu virzienu — maketu sagatavošanu iepakojuma fleksogrāfiskai drukāšanai."
          },
          {
            "type": "text",
            "content": "Galvenie sasniegumi:"
          },
          {
            "type": "list",
            "items": [
              "Pusgada laikā sasniedzu pieredzējušu speciālistu līmeni un tiku paaugstināts līdz vecākajam maketētājam",
              "Atradu risinājumus digitālo dizainu adaptēšanai analogajai fleksodrukai",
              "Pārbaudīju un koordinēju citu maketētāju darbu",
              "Sagatavoju krāsu paraugus pasūtītāju apstiprināšanai",
              "Aizvietoju projektu vadītāju atvaļinājuma laikā — veiksmīgi tiku galā (1 konsultācija 2 nedēļās pret parastajiem 45+)"
            ]
          },
          {
            "type": "text",
            "content": "Īpaši novērtēju komandas pieeju: ikdienas projektu apspriedes, kopīgu risinājumu meklēšanu, iespēju ietekmēt tehnoloģisko procesu. Vadība plānoja nodot manā kontrolē plēvju drukāšanas un formu izgatavošanas nodaļas."
          }
        ]
      },
      {
        "period": "2001 – 2006",
        "position": "Pirmsdrukas meistars",
        "company": "Litera VS",
        "duration": "5 gadi",
        "additionalInfo": [
          {
            "type": "text",
            "content": "Izdevniecības \"Fenster\" reorganizācija: pirmsdrukas sagatavošanas nodaļa tiek izdalīta atsevišķā kompānijā - \"Litera VS\". Mēs kļūstam vairāk orientēti uz ārējiem pasūtījumiem un darbu ar klientiem. Attīstoties digitālajai fotogrāfijai, profesionālā skenēšana zaudē aktualitāti. Iegādājoties Roland printeri, mēs iekļaujamies lielformāta drukas tirgū."
          },
          {
            "type": "text",
            "content": "Jauno uzdevumu skaitā:"
          },
          {
            "type": "list",
            "items": [
              "Lielformāta materiālu druka (plakāti, baneri, uzlīmes)",
              "Iekārtas apkalpošana un kontrole"
            ]
          },
          {
            "type": "text",
            "content": "Šajā periodā sāku studijas bakalaura programmā \"Vadības zinātnes\", apvienojot darbu un mācības."
          }
        ]
      },
      {
        "period": "1999 – 2001",
        "position": "Pirmsdrukas meistars",
        "company": "Izdevniecības Nams Fenster",
        "duration": "1 gads un 9 mēneši",
        "additionalInfo": [
          {
            "type": "text",
            "content": "Karjeru sāku lielā izdevniecības namā “Fenster”. Strādāju pirmsdrukas sagatavošanas nodaļā (Reprocentrs)."
          },
          {
            "type": "text",
            "content": "Galvenie pienākumi:"
          },
          {
            "type": "list",
            "items": [
              "Filmu drukāšana paša izdevniecības vajadzībām un ārējiem pasūtītājiem",
              "Specializēto iekārtu apkalpošana un kontrole",
              "Profesionāla attēlu skenēšana un apstrāde (aktuāli analogās fotogrāfijas laikmetā)",
              "Pasūtītāju konsultēšana failu sagatavošanas un krāsu dalīšanas jautājumos",
              "Maketu izstrāde un failu adaptēšana drukai"
            ]
          }
        ]
      },
      {
        "period": "1997 – 1999",
        "position": "Transporta dispečers",
        "company": "Malttrans",
        "duration": "1 gads un 3 mēneši",
        "additionalInfo": [
          {
            "type": "text",
            "content": "Dispečera amats starptautiskajā autotransporta uzņēmumā – pirmais darbs, kurā noderēja manas datorprasmes un zināšanas."
          },
          {
            "type": "text",
            "content": "Galvenie pienākumi:"
          },
          {
            "type": "list",
            "items": [
              "Autotransporta dokumentu (t.sk. TIR-Carnet) noformēšana starptautiskajiem pārvadājumiem",
              "Sadarbība ar partneriem un piegādātājiem operatīvu jautājumu risināšanai",
              "Vadītāja atsevišķu uzdevumu izpilde (vīzu noformēšana, dokumentu piegāde u.c.)",
              "Dokumentu aprites kārtošana un paātrināšana"
            ]
          },
          {
            "type": "text",
            "content": "Strādāju bez kļūdām daudzuzdevumu un augstas intensitātes apstākļos. Uzstādīju rekordu par ilgāko darba laiku amatā, kur darbinieki parasti ilgi nepalika."
          }
        ]
      },
      {
        "period": "aug. – dec. 1997",
        "position": "Autoatslēdznieka māceklis, autoelektriķis",
        "company": "Autoserviss \"KAR\"",
        "duration": "4 mēneši",
        "additionalInfo": [
          {
            "type": "text",
            "content": "Pēc Rīgas Tehniskās koledžas beigšanas iekārtojos autoservisā \"KAR\" par autoatslēdznieka mācekli un autoelektriķi."
          },
          {
            "type": "text",
            "content": "Galvenie pienākumi:"
          },
          {
            "type": "list",
            "items": [
              "Automašīnu elektroiekārtu diagnostika un nelieli remontdarbi",
              "Palīdzība meistariem atslēdznieku darbos"
            ]
          },
          {
            "type": "text",
            "content": "Izprotu automašīnas uzbūvi un apguvu darbu ar instrumentiem. Koledžā iegūtās zināšanas noderēja elektroiekāṭu diagnostikā."
          }
        ]
      }
    ]
  },
  "portfolio": {
    "title": "Portfolio",
    "tabs": {
      "static": {
        "text": "Statiskais dizains",
        "icon": "fa-solid fa-image"
      },
      "video": {
        "text": "Video materiāli",
        "icon": "fas fa-video"
      },
      "gif": {
        "text": "GIF animācija",
        "icon": "fas fa-film"
      },
      "flash": {
        "text": "Flash animācija",
        "icon": "fas fa-archive"
      },
      "flexography": {
        "text": "Fleksogrāfijai",
        "icon": "fas fa-paint-roller"
      },
      "3d": {
        "text": "3D modeļi",
        "icon": "fas fa-cube"
      }
    },
    "flexography": {
      "title": "Fleksogrāfijas projekti",
      "header": "SIA Impress — fleksogrāfija (8 krāsas, analogās formas)",
      "projects": [
        {
          "type": "left",
          "texts": [
            "Drukas paraugi līdz un pēc apstrādes ar mašīnas profilu.",
            "Rezultāts pārliecināja pasūtītāju atteikties no iepriekšējās tipogrāfijas ar digitālajām formām."
          ],
          "images": [
            {
              "src": "assets/portfolio/flexography/MajonezeBad.jpg",
              "alt": "Pirms apstrādes"
            },
            {
              "src": "assets/portfolio/flexography/MojonezeGood.jpg",
              "alt": "Pēc apstrādes"
            }
          ]
        },
        {
          "type": "right",
          "texts": [
            "Attēlā redzams gatavs makets.",
            "Pasūtītājs pārgāja uz fleksogrāfiju no rotācijas dobspieduma (rotogravure)."
          ],
          "images": [
            {
              "src": "assets/portfolio/flexography/calis_Cool.jpg",
              "alt": "Gatavs makets"
            }
          ]
        }
      ]
    },
    "flashProjects": [
      {
        "type": "featured",
        "title": "Flash-projekts Latvijas Dzelzceļam",
        "description": "Stacijas dežurantu apmācība rīcībai ārkārtas situācijās",
        "features": [
          "Dispečera pults interaktīvā interfeisa izstrāde",
          "Diktora audio pavadījuma sinhronizācija ar vizuālajiem elementiem"
        ],
        "image": {
          "src": "assets/portfolio/flash/ldz_portfolio_600x510.jpg",
          "width": 600,
          "height": 510,
          "alt": "LDZ dispečera apmācības sistēma"
        },
        "note": "Projekts satur konfidenciālu informāciju - demonstrēts anonimizētā veidā"
      }
    ],
    "3d": {
      "title": "3D modeļi",
      "project": {
        "title": "Izveidots pēc reāla klientu termināla (Cinema 4D)",
        "description": "Modelis tika izmantots uzņēmumā vizuālajām prezentācijām.",
        "realPhotoAlt": "Reālie klientu termināli",
        "render1Alt": "Render 1",
        "render2Alt": "Render 2",
        "sketchfabTitle": "Klientu termināls"
      }
    }
  },
  "contact": {
    "title": "Sazināties",
    "description": "Jūs varat sazināties ar mani, izmantojot šādas metodes:",
    "email": "alexbob@inbox.lv",
    "phone": "(+371) 29597808",
    "address": "Rīga",
    "social": {
      "linkedin": "#",
      "github": "#",
      "telegram": "#"
    }
  }
}